LICENSE
README.md
setup.cfg
setup.py
AnalyTechs.egg-info/PKG-INFO
AnalyTechs.egg-info/SOURCES.txt
AnalyTechs.egg-info/dependency_links.txt
AnalyTechs.egg-info/entry_points.txt
AnalyTechs.egg-info/requires.txt
AnalyTechs.egg-info/top_level.txt
DataExploration/__init__.py
DataExploration/bivariate.py
DataExploration/univariate.py
tests/__init__.py
tests/test1.py
tests/test2.py