Metadata-Version: 2.1
Name: AnalyTechs
Version: 0.1.0
Summary: data exploration python library use for applying different foundational techniques such as univariate, bivariate and multivariate analysis.
Home-page: https://github.com/iyaniyan11
Author: Christian Garcia
Author-email: iyaniyan3112003@gmail.com
License: MIT
Classifier: Programming Language :: Python :: 3
Classifier: License :: OSI Approved :: MIT License
Classifier: Operating System :: OS Independent
Classifier: Topic :: Software Development :: Libraries :: Python Modules
License-File: LICENSE
Requires-Dist: matplotlib>=3.4.3
Requires-Dist: numpy>=1.21.0
Requires-Dist: pandas>=1.3.3
Requires-Dist: scikit-learn>=0.24.2
